fluidstate/__init__.py
fluidstate/py.typed
fluidstate-1.1.0a8.dist-info/LICENSE
fluidstate-1.1.0a8.dist-info/METADATA
fluidstate-1.1.0a8.dist-info/WHEEL
fluidstate-1.1.0a8.dist-info/top_level.txt
fluidstate-1.1.0a8.dist-info/RECORD
